setup.cfg
setup.py
gmrh/RepoConfigParser.py
gmrh/RepositoryHandler.py
gmrh/__init__.py
gmrh.egg-info/PKG-INFO
gmrh.egg-info/SOURCES.txt
gmrh.egg-info/dependency_links.txt
gmrh.egg-info/entry_points.txt
gmrh.egg-info/top_level.txt