Metadata-Version: 1.0
Name: gmrh
Version: 0.1-dev
Summary: Easy tool for managing multiple git repositories.
Home-page: UNKNOWN
Author: Chris Trotman
Author-email: chris+gmrh@trotman.io
License: BSD
Platform: UNKNOWN
